{
    "total": [
        {
            "id": "100004221366339",
            "count": 0
        },
        {
            "id": "100057614914995",
            "count": 0
        },
        {
            "id": "100075002107641",
            "count": 0
        },
        {
            "id": "100075210332357",
            "count": 0
        },
        {
            "id": "100075321739061",
            "count": 0
        },
        {
            "id": "100077376218103",
            "count": 0
        },
        {
            "id": "100079051638922",
            "count": 0
        },
        {
            "id": "100079091494907",
            "count": 1
        },
        {
            "id": "100079300937214",
            "count": 0
        },
        {
            "id": "100081032142533",
            "count": 0
        },
        {
            "id": "100083381528473",
            "count": 0
        }
    ],
    "week": [
        {
            "id": "100004221366339",
            "count": 0,
            "name": "Nguyễn Thanh Sang"
        },
        {
            "id": "100057614914995",
            "count": 0,
            "name": "ʚHồng Ngânɞ"
        },
        {
            "id": "100075002107641",
            "count": 0,
            "name": "Nguyễn T.Hà"
        },
        {
            "id": "100075210332357",
            "count": 0,
            "name": "Vũ Hoàng Nhã Kỳ"
        },
        {
            "id": "100075321739061",
            "count": 0,
            "name": "ʚGái Ngoan Truyền Kìɞ"
        },
        {
            "id": "100077376218103",
            "count": 0,
            "name": "Vuong Hong Khanh"
        },
        {
            "id": "100079051638922",
            "count": 0,
            "name": "Người dùng Facebook"
        },
        {
            "id": "100079091494907",
            "count": 0,
            "name": "Hương Giang Nguyễn"
        },
        {
            "id": "100079300937214",
            "count": 0,
            "name": "ʚBánh Canh Chả Cáɞ"
        },
        {
            "id": "100081032142533",
            "count": 0,
            "name": "Ng Han"
        },
        {
            "id": "100083381528473",
            "count": 0,
            "name": "Ánh Hủ"
        }
    ],
    "day": [
        {
            "id": "100004221366339",
            "count": 0,
            "name": "Người dùng Facebook"
        },
        {
            "id": "100057614914995",
            "count": 0,
            "name": "ʚHồng Ngânɞ"
        },
        {
            "id": "100075002107641",
            "count": 0,
            "name": "Nguyễn T.Hà"
        },
        {
            "id": "100075210332357",
            "count": 0,
            "name": "Vũ Hoàng Nhã Kỳ"
        },
        {
            "id": "100075321739061",
            "count": 0,
            "name": "ʚGái Ngoan Truyền Kìɞ"
        },
        {
            "id": "100077376218103",
            "count": 0,
            "name": "Vuong Hong Khanh"
        },
        {
            "id": "100079051638922",
            "count": 0,
            "name": "Người dùng Facebook"
        },
        {
            "id": "100079091494907",
            "count": 0,
            "name": "Hương Giang Nguyễn"
        },
        {
            "id": "100079300937214",
            "count": 0,
            "name": "ʚBánh Canh Chả Cáɞ"
        },
        {
            "id": "100081032142533",
            "count": 0,
            "name": "Ng Han"
        },
        {
            "id": "100083381528473",
            "count": 0,
            "name": "Ánh Hủ"
        }
    ],
    "time": 6
}